crab_dbg/__init__.py
crab_dbg/_dbg.py
crab_dbg-0.1.5.dist-info/licenses/LICENSE
crab_dbg-0.1.5.dist-info/METADATA
crab_dbg-0.1.5.dist-info/WHEEL
crab_dbg-0.1.5.dist-info/top_level.txt
crab_dbg-0.1.5.dist-info/RECORD
