Metadata-Version: 2.4
Name: crab_dbg
Version: 0.1.5
Summary: Python equivalent to Rust's `dbg!()` macro
Author-email: Wenqing Zong <wenqing.zong98@gmail.com>
License-Expression: GPL-3.0-or-later
Project-URL: repository, https://github.com/WenqingZong/crab_dbg
Keywords: dbg,debug,rust
Requires-Python: >=3.10
License-File: LICENSE
Dynamic: license-file
